bixai/__init__.py
bixai/creating_dataset.py
bixai/exploring_dataset.py
bixai/forecasting_models.py
bixai/generate_example_data.py
bixai/logistic_regression_decomp.py
bixai/make_html.py
bixai/ml_models.py
bixai/model_visual_functions.py
bixai/visualizing_dataset.py
bixai-0.2.5.dist-info/LICENSE.txt
bixai-0.2.5.dist-info/METADATA
bixai-0.2.5.dist-info/WHEEL
bixai-0.2.5.dist-info/top_level.txt
bixai-0.2.5.dist-info/RECORD
