Metadata-Version: 2.1
Name: bixai
Version: 0.2.5
Summary: Package that makes it a bit easier to understand some complex models and helps you visualize them
Home-page: UNKNOWN
Author: Simon Teggelaar
Author-email: simonteggelaar@gmail.com
License: MIT
Platform: UNKNOWN
Classifier: Programming Language :: Python :: 3
Classifier: License :: OSI Approved :: MIT License
Classifier: Operating System :: OS Independent
License-File: LICENSE.txt
Requires-Dist: pandas
Requires-Dist: scipy
Requires-Dist: plotly
Requires-Dist: statsmodels
Requires-Dist: tqdm
Requires-Dist: xgboost
Requires-Dist: scikit-learn
Requires-Dist: requests
Requires-Dist: joblib
